audixa/__init__.py
audixa/_api.py
audixa/async_client.py
audixa/client.py
audixa/config.py
audixa/exceptions.py
audixa/py.typed
audixa/utils.py
audixa-0.2.5.dist-info/licenses/LICENSE
audixa-0.2.5.dist-info/METADATA
audixa-0.2.5.dist-info/WHEEL
audixa-0.2.5.dist-info/top_level.txt
audixa-0.2.5.dist-info/RECORD
