Metadata-Version: 2.4
Name: audixa
Version: 0.2.5
Summary: Official Python SDK for Audixa AI Text-to-Speech API
Author-email: Audixa AI <support@audixa.ai>, Anurag Sharma <anurag@alactic.net>
License: MIT
Project-URL: Homepage, https://audixa.ai
Project-URL: Documentation, https://docs.audixa.ai
Project-URL: Repository, https://github.com/audixaAI/audixa-python-sdk
Project-URL: Issues, https://github.com/audixaAI/audixa-python-sdk/issues
Keywords: tts,text-to-speech,audixa,ai,voice,audio,speech-synthesis
Classifier: Development Status :: 4 - Beta
Classifier: Intended Audience :: Developers
Classifier: License :: OSI Approved :: MIT License
Classifier: Operating System :: OS Independent
Classifier: Programming Language :: Python :: 3
Classifier: Programming Language :: Python :: 3.10
Classifier: Programming Language :: Python :: 3.11
Classifier: Programming Language :: Python :: 3.12
Classifier: Topic :: Multimedia :: Sound/Audio :: Speech
Classifier: Typing :: Typed
Requires-Python: >=3.10
License-File: LICENSE
Requires-Dist: requests>=2.28.0
Requires-Dist: aiohttp>=3.8.0
Provides-Extra: dev
Requires-Dist: pytest>=7.0; extra == "dev"
Requires-Dist: pytest-asyncio>=0.21; extra == "dev"
Requires-Dist: black>=23.0; extra == "dev"
Requires-Dist: mypy>=1.0; extra == "dev"
Requires-Dist: ruff>=0.1; extra == "dev"
Dynamic: license-file
